nano_chem/network/base_network.py
nano_chem/utils/common_utils.py
nano_chem/utils/logger_cls.py
nano_chem-0.1.0.dist-info/WHEEL
nano_chem-0.1.0.dist-info/METADATA
nano_chem-0.1.0.dist-info/RECORD
