Metadata-Version: 2.1
Name: nano-chem
Version: 0.1.0
Summary: A Deep Learning Library for Chemistry.
Home-page: https://github.com/
License: MIT
Keywords: nanp,deep learning,chemistry
Author: Xiaomin Wu
Author-email: xmwu@mail.ustc.edu.cn
Requires-Python: >=3.7,<4.0
Classifier: License :: OSI Approved :: MIT License
Classifier: Programming Language :: Python :: 3
Classifier: Programming Language :: Python :: 3.7
Classifier: Programming Language :: Python :: 3.8
Requires-Dist: ace (>=0.3.2,<0.4.0)
Requires-Dist: matplotlib (>=3.3.0,<4.0.0)
Requires-Dist: numpy (>=1.19.0,<2.0.0)
Requires-Dist: pandas (>=1.0.5,<2.0.0)
Requires-Dist: tensorflow (>=2.2.0,<3.0.0)
Requires-Dist: torch (>=1.5.1,<2.0.0)
Project-URL: Documentation, https://
Project-URL: Repository, https://
